__init__.py
compile_circuit.py
default_pass.py
main.py
stubs.py
tkr_pytket_worker-0.1.4.dist-info/METADATA
tkr_pytket_worker-0.1.4.dist-info/WHEEL
tkr_pytket_worker-0.1.4.dist-info/entry_points.txt
tkr_pytket_worker-0.1.4.dist-info/RECORD
